kardocss/__init__.py
kardocss/cli/__init__.py
kardocss/cli/build.py
kardocss/compiler/__init__.py
kardocss/compiler/compiler.py
kardocss/compiler/purge.py
kardocss/compiler/responsive.py
kardocss/core/__init__.py
kardocss/core/config.py
kardocss/utilities/__init__.py
kardocss/utilities/admin.py
kardocss/utilities/badges.py
kardocss/utilities/borders.py
kardocss/utilities/colors.py
kardocss/utilities/components.py
kardocss/utilities/container_queries.py
kardocss/utilities/dark_mode.py
kardocss/utilities/effects.py
kardocss/utilities/forms.py
kardocss/utilities/gradients.py
kardocss/utilities/layout.py
kardocss/utilities/sizing.py
kardocss/utilities/spacing.py
kardocss/utilities/tv_breakpoints.py
kardocss/utilities/typography.py
kardocss-1.2.0.dist-info/licenses/LICENSE
kardocss-1.2.0.dist-info/METADATA
kardocss-1.2.0.dist-info/WHEEL
kardocss-1.2.0.dist-info/entry_points.txt
kardocss-1.2.0.dist-info/top_level.txt
kardocss-1.2.0.dist-info/RECORD
